README.md
setup.py
timsdk/__init__.py
timsdk/error_code.py
timsdk/http_client.py
timsdk/tim_client.py
timsdk/tls_sig.py
timsdk.egg-info/PKG-INFO
timsdk.egg-info/SOURCES.txt
timsdk.egg-info/dependency_links.txt
timsdk.egg-info/requires.txt
timsdk.egg-info/top_level.txt
timsdk/api/__init__.py
timsdk/api/base.py
timsdk/api/group_open_http_svc.py
timsdk/api/im_open_login_svc.py
timsdk/api/open_config_svr.py
timsdk/api/open_im.py
timsdk/api/open_msg_svc.py
timsdk/api/profile.py
timsdk/api/sns.py