Metadata-Version: 1.1
Name: timsdk
Version: 1.1.12
Summary: A package for qcloud im(tim), Implement REST API.
Home-page: https://github.com/WUWUTech/timsdk
Author: Severus Well
Author-email: thinkweiwei@msn.com
License: UNKNOWN
Keywords: qcloud,Tencent,im,tim,SDK
Platform: UNKNOWN
Classifier: Environment :: Console
Classifier: Operating System :: MacOS :: MacOS X
Classifier: Operating System :: Microsoft :: Windows
Classifier: Operating System :: POSIX
Classifier: Programming Language :: Python
Classifier: Programming Language :: Python :: 3.5
Classifier: Programming Language :: Python :: 3.6
Classifier: Programming Language :: Python :: 3.7
